point_cloud_utils/__init__.py
point_cloud_utils/_mesh_io.py
point_cloud_utils/_mesh_primitives.py
point_cloud_utils/_pcu_internal.cpython-311-darwin.so
point_cloud_utils/_point_cloud_geometry.py
point_cloud_utils/_pointcloud_normals.py
point_cloud_utils/_ray_mesh_intersector.py
point_cloud_utils/_ray_point_cloud_intersector.py
point_cloud_utils/_sinkhorn.py
point_cloud_utils/_voxels.py
point_cloud_utils-0.34.0.dist-info/licenses/LICENSE
point_cloud_utils-0.34.0.dist-info/METADATA
point_cloud_utils-0.34.0.dist-info/WHEEL
point_cloud_utils-0.34.0.dist-info/top_level.txt
point_cloud_utils-0.34.0.dist-info/RECORD
