Metadata-Version: 2.1
Name: point-cloud-utils
Version: 0.34.0
Summary: A Python library for common tasks on 3D point clouds and meshes
Home-page: https://github.com/fwilliams/point-cloud-utils
Author: Francis Williams
Author-email: francis@fwilliams.info
Classifier: Programming Language :: C++
Classifier: Programming Language :: Python :: 3
Classifier: License :: OSI Approved :: MIT License
License-File: LICENSE
Requires-Dist: numpy
Requires-Dist: scipy
